Workbook

Sheet Cover
A1: Nike INC- Intrinsic Valuation (DCF)
A2: Equity Research / Investment Banking Style Model
A4: Methodology
A5: Unlevered Discounted Cash Flow
A6: Explicit forecast period: FY2025E-FY2029E
A7: Terminal Value: Perpetuity growth method
A9: Key Assumptions
A10: WACC: 8.1%
A11: Terminal growth rate: 2.5%
A12: Tax Rate: effective rate
A13: Forecast driven by revenue growth and EBIT margin expansion
A15: Valuation Output (Base Case)
... A28: This model estimates Nike’s intrinsic equity value under normalized growth, margin, and cost-of-capital assumptions to assess whether the current market valuation implies realistic operating outcomes.

Sheet Assumptions
A1: Assumption Name | B1: Rational/Source | C1: FY2025 | D1: FY2026 | E1: FY2027 | F1: FY2028 | G1: FY2029
A2: Revenue Growth % | B2: Normalized growth for mature global brand | C2: 0.05 | D2: 0.045 | E2: 0.04 | F2: 0.035 | G2: 0.03
A3: EBIT Margin % | B3: Margin recovery toward historical mid-teens | C3: 0.125 | D3: 0.13 | E3: 0.135 | F3: 0.14 | G3: 0.14
A4: Effective Tax Rate | B4: Normalized historical effective rate | C4: 0.18 | D4: 0.18 | E4: 0.18 | F4: 0.18 | G4: 0.18
A5: D&A Assumptions | B5: Historical average depreication intensity | C5: 0.015 | D5: 0.015 | E5: 0.015 | F5: 0.015 | G5: 0.015
A6: CapEx % of Revenue | B6: Maintenece and growth capital spending | C6: -0.02 | D6: -0.02 | E6: -0.02 | F6: -0.02 | G6: -0.02
A7: Change in WC % of Revenue | B7: Normalized wokring capital investment | C7: -0.005 | D7: -0.005 | E7: -0.005 | F7: -0.005 | G7: -0.005

Sheet DCF Valuation
A1: DCF Valuation | B1: FY2025E | C1: FY2026E | D1: FY2027E | E1: FY2028E | F1: FY2029E
A2: “DCF implies ~$87/share based on 8.1% WACC and 2.5% terminal growth.”
A3: WACC Assumptions
A5: Risk-Free Rate | B5: 0.04
A6: Equity Risk Premium | B6: 0.055
A7: Beta | B7: 1.1
A8: Cost of Equity | B8: =B5+B7*B6 -> 0.1005
A10: Cost of Debt (Pre-Tax) | B10: 0.045
A11: Tax Rate | B11: 0.18
A12: Cost of Debt (After-Tax) | B12: =B10*(1-B11) -> 0.0369
A14: Target Debt % | B14: 0.3
A15: Target Equity % | B15: 0.7
A16: WACC | B16: =B8*B15+B12*B14 -> 0.08142
A18: Discout Factor | B18: =1/(1+$B$16)^1 -> 0.9247101 | C18: =1/(1+$B$16)^2 -> 0.85508878 | D18: =1/(1+$B$16)^3 -> 0.79070923 | E18: =1/(1+$B$16)^4 -> 0.73117681 | F18: =1/(1+$B$16)^5 -> 0.67612659
A20: Unlevered Free Cash Flow | B20: ='Operating Forecast'!C16 -> 4988.5342 | C20: ='Operating Forecast'!D16 -> 5444.0818 | D20: ='Operating Forecast'!E16 -> 5902.1511 | E20: ='Operating Forecast'!F16 -> 6357.4432 | F20: ='Operating Forecast'!G16 -> 6548.1665
A21: PV of Unlevered Free Cash Flow | B21: =B20*B18 -> 4612.948 | C21: =C20*C18 -> 4655.1732 | D21: =D20*D18 -> 4666.8854 | E21: =E20*E18 -> 4648.4151 | F21: =F20*F18 -> 4427.3895
A23: Terminal Growth Rate | B23: 0.025
A24: Terminal Value | F24: =F20 * (1 + $B$23) / ($B$16 - $B$23) -> 118962.61
A25: PV of Terminal Value | F25: =F24*F18 -> 80433.786
A26: Enterprise Value | B26: =SUM(B21:F21) + F25 -> 103444.6
A28: Cash & Equivalents | B28: ='Historical Financials'!F17 -> 9860
A29: Total Debt | B29: ='Historical Financials'!F18 -> 8903
A30: Net Debt (Cash - Debt) | B30: =B29-B28 -> -957
A31: Equity Value | B31: =B26-B30 -> 104401.6
A32: Diluted Shares Outstanding | B32: ='Historical Financials'!F19 -> 1205
A33: Implied Share Price | B33: =B31/B32 -> 86.640329

Sheet Historical Financials
B1: FY 2020 | C1: FY 2021 | D1: FY 2022 | E1: FY 2023 | F1: FY 2024
A2: Income Statment (USD Millions)
A3: Revenue | B3: 37403 | C3: 44538 | D3: 46710 | E3: 51217 | F3: 51362
A4: Operating Income (EBIT) | B4: 2887 | C4: 6736 | D4: 6651 | E4: 5915 | F4: 6311
A5: EBIT Margin % | B5: =B4/B3 -> 0.077186322 | C5: =C4/C3 -> 0.15124164 | D5: =D4/D3 -> 0.14238921 | E5: =E4/E3 -> 0.115489 | F5: =F4/F3 -> 0.12287294
A6: Revenue Growth % | C6: =(C3/B3)-1 -> 0.1907601 | D6: =(D3/C3)-1 -> 0.048767345 | E6: =(E3/D3)-1 -> 0.096488975 | F6: =(F3/E3)-1 -> 0.0028310912
A8: Cash Flow Statement
A9: Deprecaition and Amortization | B9: 705 | C9: 1258 | D9: 721 | E9: 703 | F9: 796
A10: D&A % of Revenue | B10: =B9/B3 -> 0.018848755 | C10: =C9/C3 -> 0.028245543 | D10: =D9/D3 -> 0.015435667 | E10: =E9/E3 -> 0.013725911 | F10: =F9/F3 -> 0.015497839
A11: Capital Expenditures | B11: -1028 | C11: -973 | D11: -1086 | E11: -969 | F11: -812
A12: CapEx % of Revenue | B12: =B11/B3 -> -0.027484426 | C12: =C11/C3 -> -0.021846513 | D12: =D11/D3 -> -0.023249839 | E12: =E11/E3 -> -0.018919499 | F12: =F11/F3 -> -0.015809353
A13: Change in Working Capital | B13: 23 | C13: -2427 | D13: 24 | E13: -513 | F13: 716
A14: Change WC % of Revenue | B14: =B13/B3 -> 0.00061492394 | C14: =C13/C3 -> -0.054492793 | D14: =D13/D3 -> 0.00051380861 | E14: =E13/E3 -> -0.010016206 | F14: =F13/F3 -> 0.013940267
A16: Balance Sheet
A17: Cash & Equivalents | B17: 8348 | C17: 9889 | D17: 8574 | E17: 7441 | F17: 9860
A18: Total Debt | B18: 9412 | C18: 10920 | D18: 9420 | E18: 8927 | F18: 8903
A19: Shares Outstanding (Diluted, mm) | B19: 1592 | C19: 1579 | D19: 1611 | E19: 1266 | F19: 1205

Sheet Operating Forecast
A1: Forecast Financials (USD millions) | B1: FY2024A | C1: FY2025E | D1: FY2026E | E1: FY2027E | F1: FY2028E | G1: FY2029E
A3: Revenue | B3: ='Historical Financials'!F3 -> 51362 | C3: =B3*(1+C4) -> 53930.1 | D3: =C3*(1+D4) -> 56356.954 | E3: =D3*(1+E4) -> 58611.233 | F3: =E3*(1+F4) -> 60662.626 | G3: =F3*(1+G4) -> 62482.505
A4: Revenue Growth % | C4: =Assumptions!C2 -> 0.05 | D4: =Assumptions!D2 -> 0.045 | E4: =Assumptions!E2 -> 0.04 | F4: =Assumptions!F2 -> 0.035 | G4: =Assumptions!G2 -> 0.03
A6: EBIT Margin % | C6: =Assumptions!C3 -> 0.125 | D6: =Assumptions!D3 -> 0.13 | E6: =Assumptions!E3 -> 0.135 | F6: =Assumptions!F3 -> 0.14 | G6: =Assumptions!G3 -> 0.14
A7: EBIT | B7: ='Historical Financials'!F4 -> 6311 | C7: =C3*C6 -> 6741.2625 | D7: =D3*D6 -> 7326.4041 | E7: =E3*E6 -> 7912.5164 | F7: =F3*F6 -> 8492.7676 | G7: =G3*G6 -> 8747.5506
A9: Tax @ Effective Rate | C9: =-C7*Assumptions!C4 -> -1213.4272 | D9: =-D7*Assumptions!D4 -> -1318.7527 | E9: =-E7*Assumptions!E4 -> -1424.253 | F9: =-F7*Assumptions!F4 -> -1528.6982 | G9: =-G7*Assumptions!G4 -> -1574.5591
A10: NOPAT | C10: =C7+C9 -> 5527.8353 | D10: =D7+D9 -> 6007.6514 | E10: =E7+E9 -> 6488.2635 | F10: =F7+F9 -> 6964.0694 | G10: =G7+G9 -> 7172.9915
A12: Depreciation & Amortization | C12: =C3*Assumptions!C5 -> 808.9515 | D12: =D3*Assumptions!D5 -> 845.35432 | E12: =E3*Assumptions!E5 -> 879.16849 | F12: =F3*Assumptions!F5 -> 909.93939 | G12: =G3*Assumptions!G5 -> 937.23757
A13: Capital Expenditures | C13: =C3*Assumptions!C6 -> -1078.602 | D13: =D3*Assumptions!D6 -> -1127.1391 | E13: =E3*Assumptions!E6 -> -1172.2247 | F13: =F3*Assumptions!F6 -> -1213.2525 | G13: =G3*Assumptions!G6 -> -1249.6501
A14: Change in Working Capital | C14: =C3*Assumptions!C7 -> -269.6505 | D14: =D3*Assumptions!D7 -> -281.78477 | E14: =E3*Assumptions!E7 -> -293.05616 | F14: =F3*Assumptions!F7 -> -303.31313 | G14: =G3*Assumptions!G7 -> -312.41252
A16: Unlevered Free Cash Flow | C16: =C10+C12+C13+C14 -> 4988.5342 | D16: =D10+D12+D13+D14 -> 5444.0818 | E16: =E10+E12+E13+E14 -> 5902.1511 | F16: =F10+F12+F13+F14 -> 6357.4432 | G16: =G10+G12+G13+G14 -> 6548.1665

Sheet Sensitivity
A1: Implied Share Price Sensitivity ($)
C3: 0.02 | D3: 0.0225 | E3: 0.025 | F3: 0.0275 | G3: 0.03
B4: 0.075 | C4: =IFERROR( ( ( ( 'DCF Valuation'!F20 * (1 + C$3) ) / ($B4 - C$3) ) * 'DCF Valuation'!F18 + SUM('DCF Valuation'!B21:F21) - 'DCF Valuation'!B29 + 'DCF Valuation'!B28 ) / 'DCF Valuation'!B32, "" ) -> 88.029677 | D4: =((('DCF Valuation'!F20*(1+D$3))/($B4-D$3))*'DCF Valuation'!F18 +SUM('DCF Valuation'!B21:F21) -'DCF Valuation'!B29 +'DCF Valuation'!B28) /'DCF Valuation'!B32 -> 91.449371 | E4: =((('DCF Valuation'!F20*(1+E$3))/($B4-E$3))*'DCF Valuation'!F18 +SUM('DCF Valuation'!B21:F21) -'DCF Valuation'!B29 +'DCF Valuation'!B28) /'DCF Valuation'!B32 -> 95.211033 | F4: =((('DCF Valuation'!F20*(1+F$3))/($B4-F$3))*'DCF Valuation'!F18 +SUM('DCF Valuation'!B21:F21) -'DCF Valuation'!B29 +'DCF Valuation'!B28) /'DCF Valuation'!B32 -> 99.36866 | G4: =((('DCF Valuation'!F20*(1+G$3))/($B4-G$3))*'DCF Valuation'!F18 +SUM('DCF Valuation'!B21:F21) -'DCF Valuation'!B29 +'DCF Valuation'!B28) /'DCF Valuation'!B32 -> 103.98825 | I4: WACC | J4: ='DCF Valuation'!B16 -> 0.08142
B5: 0.08 | C5: =( ( ('DCF Valuation'!F20*(1+C$3))/($B5-C$3) )*'DCF Valuation'!F18 +SUM('DCF Valuation'!B21:F21) -'DCF Valuation'!B29 +'DCF Valuation'!B28 ) /'DCF Valuation'!B32 -> 82.351396 | D5: =((('DCF Valuation'!F20*(1+D$3))/($B5-D$3))*'DCF Valuation'!F18 +SUM('DCF Valuation'!B21:F21) -'DCF Valuation'!B29 +'DCF Valuation'!B28) /'DCF Valuation'!B32 -> 85.226843 | E5: =((('DCF Valuation'!F20*(1+E$3))/($B5-E$3))*'DCF Valuation'!F18 +SUM('DCF Valuation'!B21:F21) -'DCF Valuation'!B29 +'DCF Valuation'!B28) /'DCF Valuation'!B32 -> 88.363694 | F5: =((('DCF Valuation'!F20*(1+F$3))/($B5-F$3))*'DCF Valuation'!F18 +SUM('DCF Valuation'!B21:F21) -'DCF Valuation'!B29 +'DCF Valuation'!B28) /'DCF Valuation'!B32 -> 91.799293 | G5: =((('DCF Valuation'!F20*(1+G$3))/($B5-G$3))*'DCF Valuation'!F18 +SUM('DCF Valuation'!B21:F21) -'DCF Valuation'!B29 +'DCF Valuation'!B28) /'DCF Valuation'!B32 -> 95.578451 | I5: Terminal Growth Rate | J5: ='DCF Valuation'!B23 -> 0.025
B6: 0.085 | C6: =( ( ('DCF Valuation'!F20*(1+C$3))/($B6-C$3) )*'DCF Valuation'!F18 +SUM('DCF Valuation'!B21:F21) -'DCF Valuation'!B29 +'DCF Valuation'!B28 ) /'DCF Valuation'!B32 -> 77.546696 | D6: =((('DCF Valuation'!F20*(1+D$3))/($B6-D$3))*'DCF Valuation'!F18 +SUM('DCF Valuation'!B21:F21) -'DCF Valuation'!B29 +'DCF Valuation'!B28) /'DCF Valuation'!B32 -> 79.999919 | E6: =((('DCF Valuation'!F20*(1+E$3))/($B6-E$3))*'DCF Valuation'!F18 +SUM('DCF Valuation'!B21:F21) -'DCF Valuation'!B29 +'DCF Valuation'!B28) /'DCF Valuation'!B32 -> 82.657578 | F6: =((('DCF Valuation'!F20*(1+F$3))/($B6-F$3))*'DCF Valuation'!F18 +SUM('DCF Valuation'!B21:F21) -'DCF Valuation'!B29 +'DCF Valuation'!B28) /'DCF Valuation'!B32 -> 85.546337 | G6: =((('DCF Valuation'!F20*(1+G$3))/($B6-G$3))*'DCF Valuation'!F18 +SUM('DCF Valuation'!B21:F21) -'DCF Valuation'!B29 +'DCF Valuation'!B28) /'DCF Valuation'!B32 -> 88.69771
B7: 0.09 | C7: =( ( ('DCF Valuation'!F20*(1+C$3))/($B7-C$3) )*'DCF Valuation'!F18 +SUM('DCF Valuation'!B21:F21) -'DCF Valuation'!B29 +'DCF Valuation'!B28 ) /'DCF Valuation'!B32 -> 73.428382 | D7: =((('DCF Valuation'!F20*(1+D$3))/($B7-D$3))*'DCF Valuation'!F18 +SUM('DCF Valuation'!B21:F21) -'DCF Valuation'!B29 +'DCF Valuation'!B28) /'DCF Valuation'!B32 -> 75.547355 | E7: =((('DCF Valuation'!F20*(1+E$3))/($B7-E$3))*'DCF Valuation'!F18 +SUM('DCF Valuation'!B21:F21) -'DCF Valuation'!B29 +'DCF Valuation'!B28) /'DCF Valuation'!B32 -> 77.829325 | F7: =((('DCF Valuation'!F20*(1+F$3))/($B7-F$3))*'DCF Valuation'!F18 +SUM('DCF Valuation'!B21:F21) -'DCF Valuation'!B29 +'DCF Valuation'!B28) /'DCF Valuation'!B32 -> 80.293854 | G7: =((('DCF Valuation'!F20*(1+G$3))/($B7-G$3))*'DCF Valuation'!F18 +SUM('DCF Valuation'!B21:F21) -'DCF Valuation'!B29 +'DCF Valuation'!B28) /'DCF Valuation'!B32 -> 82.963759
B8: 0.095 | C8: =( ( ('DCF Valuation'!F20*(1+C$3))/($B8-C$3) )*'DCF Valuation'!F18 +SUM('DCF Valuation'!B21:F21) -'DCF Valuation'!B29 +'DCF Valuation'!B28 ) /'DCF Valuation'!B32 -> 69.859177 | D8: =((('DCF Valuation'!F20*(1+D$3))/($B8-D$3))*'DCF Valuation'!F18 +SUM('DCF Valuation'!B21:F21) -'DCF Valuation'!B29 +'DCF Valuation'!B28) /'DCF Valuation'!B32 -> 71.708937 | E8: =((('DCF Valuation'!F20*(1+E$3))/($B8-E$3))*'DCF Valuation'!F18 +SUM('DCF Valuation'!B21:F21) -'DCF Valuation'!B29 +'DCF Valuation'!B28) /'DCF Valuation'!B32 -> 73.690824 | F8: =((('DCF Valuation'!F20*(1+F$3))/($B8-F$3))*'DCF Valuation'!F18 +SUM('DCF Valuation'!B21:F21) -'DCF Valuation'!B29 +'DCF Valuation'!B28) /'DCF Valuation'!B32 -> 75.819516 | G8: =((('DCF Valuation'!F20*(1+G$3))/($B8-G$3))*'DCF Valuation'!F18 +SUM('DCF Valuation'!B21:F21) -'DCF Valuation'!B29 +'DCF Valuation'!B28) /'DCF Valuation'!B32 -> 78.111955

Sheet Public Comps 
A1: Company | B1: Ticker | C1: EV ($bn) | D1: LTM Revenue ($bn) | E1: LTM EBTIDA | F1: EV / Revenue | G1: EV / EBTIDA
A2: Nike | B2: NKE | C2: 87.52 | D2: 46.51 | E2: 3.82 | F2: 1.88 | G2: 28.77
A3: Adidas | B3: ADDYY | C3: 39.23 | D3: 24.7 | E3: 2.43 | F3: 1.36 | G3: 10.9
A4: Lululemon | B4: LULU | C4: 25.64 | D4: 11.07 | E4: 2.94 | F4: 2.32 | G4: 8.73
A5: Puma | B5: PUM.DE | C5: 5.67 | D5: 8.26 | E5: 0.366 | F5: 0.69 | G5: 84.74
A6: Under Armour | B6: UA | C6: 3.39 | D6: 5.05 | E6: 0.232 | F6: 0.67 | G6: 20.85
A8: Trading Multiples - Median
F9: Median EV / Revenue (LTM) | G9: Median EV / EBTIDA (LTM)
F10: =MEDIAN(F2:F4,F6) -> 1.62 | G10: =MEDIAN(G2:G4,G6) -> 15.875
F12: Median excludes Puma due to outlier EBITDA multiple

Sheet Football Field 
A1: Valuation Method | B1: Low | C1: High | D1: Range
A2: EV / Revenue | B2: =((F9 * F3 * 1000) - F5) / F6 -> 53.942963 | C2: =((F10 * F3 * 1000) - F5) / F6 -> 72.701353 | D2: =C2-B2 -> 18.75839
A3: EV / EBTIDA | B3: =((F11 * F4 * 1000) - F5) / F6 -> 43.571058 | C3: =((F12 * F4 * 1000) - F5) / F6 -> 58.668776 | D3: =C3-B3 -> 15.097718 | E3: LTM Revenue | F3: ='Public Comps '!D2 -> 46.51
A4: DCF | B4: =F7 -> 86.640329 | C4: =87.1 -> 87.1 | D4: =C4-B4 -> 0.45967065 | E4: LTM EBTIDA | F4: ='Public Comps '!E2 -> 3.82
A5: Current Share Price | B5: 57.34 | C5: 57.44 | D5: =C5-B5 -> 0.1 | E5: Net Debt | F5: ='DCF Valuation'!B30 -> -957
E6: Diluted Shares | F6: ='DCF Valuation'!B32 -> 1205
E7: DCF Implied Share Price | F7: ='DCF Valuation'!B33 -> 86.640329
E9: EV / Revenue - Low Multiple | F9: 1.377
E10: EV / Revenue - High Multiple | F10: 1.863
E11: EV / EBITDA - Low Multiple | F11: 13.49375
E12: EV / EBITDA - High Multiple | F12: 18.25625
